{
  "name": "ISOCases",
  "options": {
    "idInjection": false,
    "postgresql": {
      "schema": "public",
      "table": "ISOCases"
    }
  },
  "properties": {
    "batchid": {
      "type": "String",
      "required": false,
      "length": 250,
      "precision": null,
      "scale": null,
      "postgresql": {
        "columnName": "batchid",
        "dataType": "character varying",
        "dataLength": 250,
        "dataPrecision": null,
        "dataScale": null,
        "nullable": "YES"
      }
    },
    "parentpid": {
      "type": "String",
      "required": false,
      "length": 250,
      "precision": null,
      "scale": null,
      "id": true,
      "postgresql": {
        "columnName": "parentpid",
        "dataType": "character varying",
        "dataLength": 250,
        "dataPrecision": null,
        "dataScale": null,
        "nullable": "YES"
      }
    },
    "isopid": {
      "type": "String",
      "required": false,
      "length": 250,
      "precision": null,
      "scale": null,
      "postgresql": {
        "columnName": "isopid",
        "dataType": "character varying",
        "dataLength": 250,
        "dataPrecision": null,
        "dataScale": null,
        "nullable": "YES"
      }
    },
    "caseid": {
      "type": "String",
      "required": false,
      "length": 250,
      "precision": null,
      "scale": null,
      "postgresql": {
        "columnName": "caseid",
        "dataType": "character varying",
        "dataLength": 250,
        "dataPrecision": null,
        "dataScale": null,
        "nullable": "YES"
      }
    },
    "isoindicator": {
      "type": "Number",
      "required": false,
      "length": null,
      "precision": 32,
      "scale": 0,
      "postgresql": {
        "columnName": "isoindicator",
        "dataType": "integer",
        "dataLength": null,
        "dataPrecision": 32,
        "dataScale": 0,
        "nullable": "YES"
      }
    },
    "score": {
      "type": "Number",
      "required": false,
      "length": null,
      "precision": 32,
      "scale": 0,
      "postgresql": {
        "columnName": "score",
        "dataType": "integer",
        "dataLength": null,
        "dataPrecision": 32,
        "dataScale": 0,
        "nullable": "YES"
      }
    },
    "accidentdate": {
      "type": "String",
      "required": false,
      "length": null,
      "precision": null,
      "scale": null,
      "postgresql": {
        "columnName": "accidentdate",
        "dataType": "timestamp without time zone",
        "dataLength": null,
        "dataPrecision": null,
        "dataScale": null,
        "nullable": "YES"
      }
    },
    "benefitamount": {
      "type": "String",
      "required": false,
      "length": 250,
      "precision": null,
      "scale": null,
      "postgresql": {
        "columnName": "benefitamount",
        "dataType": "character varying",
        "dataLength": 250,
        "dataPrecision": null,
        "dataScale": null,
        "nullable": "YES"
      }
    },
    "fundingsource": {
      "type": "String",
      "required": false,
      "length": 250,
      "precision": null,
      "scale": null,
      "postgresql": {
        "columnName": "fundingsource",
        "dataType": "character varying",
        "dataLength": 250,
        "dataPrecision": null,
        "dataScale": null,
        "nullable": "YES"
      }
    },
    "lob": {
      "type": "String",
      "required": false,
      "length": 250,
      "precision": null,
      "scale": null,
      "postgresql": {
        "columnName": "lob",
        "dataType": "character varying",
        "dataLength": 250,
        "dataPrecision": null,
        "dataScale": null,
        "nullable": "YES"
      }
    },
    "state": {
      "type": "String",
      "required": false,
      "length": 250,
      "precision": null,
      "scale": null,
      "postgresql": {
        "columnName": "state",
        "dataType": "character varying",
        "dataLength": 250,
        "dataPrecision": null,
        "dataScale": null,
        "nullable": "YES"
      }
    },
    "workcomp": {
      "type": "String",
      "required": false,
      "length": 250,
      "precision": null,
      "scale": null,
      "postgresql": {
        "columnName": "workcomp",
        "dataType": "character varying",
        "dataLength": 250,
        "dataPrecision": null,
        "dataScale": null,
        "nullable": "YES"
      }
    },
    "casestatus": {
      "type": "String",
      "required": false,
      "length": 250,
      "precision": null,
      "scale": null,
      "postgresql": {
        "columnName": "casestatus",
        "dataType": "character varying",
        "dataLength": 250,
        "dataPrecision": null,
        "dataScale": null,
        "nullable": "YES"
      }
    },
    "casesource": {
      "type": "String",
      "required": false,
      "length": 250,
      "precision": null,
      "scale": null,
      "postgresql": {
        "columnName": "casesource",
        "dataType": "character varying",
        "dataLength": 250,
        "dataPrecision": null,
        "dataScale": null,
        "nullable": "YES"
      }
    },
    "casetype": {
      "type": "String",
      "required": false,
      "length": 250,
      "precision": null,
      "scale": null,
      "postgresql": {
        "columnName": "casetype",
        "dataType": "character varying",
        "dataLength": 250,
        "dataPrecision": null,
        "dataScale": null,
        "nullable": "YES"
      }
    },
    "casereceived": {
      "type": "Boolean",
      "required": false,
      "length": null,
      "precision": null,
      "scale": null,
      "postgresql": {
        "columnName": "casereceived",
        "dataType": "boolean",
        "dataLength": null,
        "dataPrecision": null,
        "dataScale": null,
        "nullable": "YES"
      }
    },
    "caseidentified": {
      "type": "Boolean",
      "required": false,
      "length": null,
      "precision": null,
      "scale": null,
      "postgresql": {
        "columnName": "caseidentified",
        "dataType": "boolean",
        "dataLength": null,
        "dataPrecision": null,
        "dataScale": null,
        "nullable": "YES"
      }
    },
    "casereceivedat": {
      "type": "String",
      "required": false,
      "length": null,
      "precision": null,
      "scale": null,
      "postgresql": {
        "columnName": "casereceivedat",
        "dataType": "timestamp without time zone",
        "dataLength": null,
        "dataPrecision": null,
        "dataScale": null,
        "nullable": "YES"
      }
    },
    "caseidentifiedat": {
      "type": "String",
      "required": false,
      "length": null,
      "precision": null,
      "scale": null,
      "postgresql": {
        "columnName": "caseidentifiedat",
        "dataType": "timestamp without time zone",
        "dataLength": null,
        "dataPrecision": null,
        "dataScale": null,
        "nullable": "YES"
      }
    },
    "requestid": {
      "type": "String",
      "required": false,
      "length": 250,
      "precision": null,
      "scale": null,
      "postgresql": {
        "columnName": "requestid",
        "dataType": "character varying",
        "dataLength": 250,
        "dataPrecision": null,
        "dataScale": null,
        "nullable": "YES"
      }
    },
    "isostate": {
      "type": "String",
      "required": false,
      "length": 250,
      "precision": null,
      "scale": null,
      "postgresql": {
        "columnName": "isostate",
        "dataType": "character varying",
        "dataLength": 250,
        "dataPrecision": null,
        "dataScale": null,
        "nullable": "YES"
      }
    },
    "receivediso": {
      "type": "String",
      "required": false,
      "length": null,
      "precision": null,
      "scale": null,
      "postgresql": {
        "columnName": "receivediso",
        "dataType": "timestamp without time zone",
        "dataLength": null,
        "dataPrecision": null,
        "dataScale": null,
        "nullable": "YES"
      }
    },
    "beganisoprocessing": {
      "type": "String",
      "required": false,
      "length": null,
      "precision": null,
      "scale": null,
      "postgresql": {
        "columnName": "beganisoprocessing",
        "dataType": "timestamp without time zone",
        "dataLength": null,
        "dataPrecision": null,
        "dataScale": null,
        "nullable": "YES"
      }
    },
    "foundduplicateiso": {
      "type": "String",
      "required": false,
      "length": null,
      "precision": null,
      "scale": null,
      "postgresql": {
        "columnName": "foundduplicateiso",
        "dataType": "timestamp without time zone",
        "dataLength": null,
        "dataPrecision": null,
        "dataScale": null,
        "nullable": "YES"
      }
    },
    "fetchedisodata": {
      "type": "String",
      "required": false,
      "length": null,
      "precision": null,
      "scale": null,
      "postgresql": {
        "columnName": "fetchedisodata",
        "dataType": "timestamp without time zone",
        "dataLength": null,
        "dataPrecision": null,
        "dataScale": null,
        "nullable": "YES"
      }
    },
    "senttoiso": {
      "type": "String",
      "required": false,
      "length": null,
      "precision": null,
      "scale": null,
      "postgresql": {
        "columnName": "senttoiso",
        "dataType": "timestamp without time zone",
        "dataLength": null,
        "dataPrecision": null,
        "dataScale": null,
        "nullable": "YES"
      }
    }
  }
}
